source_instatus/__init__.py
source_instatus/components.py
source_instatus/manifest.yaml
source_instatus/run.py
source_instatus/schemas/incident_updates.json
source_instatus/schemas/incidents.json
source_instatus/schemas/maintenance_updates.json
source_instatus/schemas/maintenances.json
source_instatus/schemas/metrics.json
source_instatus/schemas/page_components.json
source_instatus/schemas/public_data.json
source_instatus/schemas/status_pages.json
source_instatus/schemas/subscribers.json
source_instatus/schemas/team.json
source_instatus/schemas/templates.json
source_instatus/schemas/user.json
source_instatus/source.py
source_instatus/spec.yaml
airbyte_source_instatus-0.1.29.dist-info/METADATA
airbyte_source_instatus-0.1.29.dist-info/WHEEL
airbyte_source_instatus-0.1.29.dist-info/entry_points.txt
airbyte_source_instatus-0.1.29.dist-info/RECORD
