Metadata-Version: 2.3
Name: airbyte-source-instatus
Version: 0.1.29
Summary: Source implementation for Instatus.
Home-page: https://airbyte.com
License: MIT
Author: Airbyte
Author-email: contact@airbyte.io
Requires-Python: >=3.9,<3.12
Classifier: License :: OSI Approved :: MIT License
Classifier: Programming Language :: Python :: 3
Classifier: Programming Language :: Python :: 3.9
Classifier: Programming Language :: Python :: 3.10
Classifier: Programming Language :: Python :: 3.11
Requires-Dist: airbyte-cdk (==1.0.0)
Project-URL: Documentation, https://docs.airbyte.com/integrations/sources/instatus
Project-URL: Repository, https://github.com/airbytehq/airbyte
